Workbook

Sheet Como usar
A1: Tracker · Modelo de Terceirização da Operação
A2: Fonte única de verdade do projeto. Gerado em 26/ago/2026 a partir da reunião Escalabilidade time.
A4: A regra que faz isso funcionar
A5: A aba Tarefas manda. Toda tarefa mexida no dia é atualizada antes de você sair — não na reunião, no dia.
A6: Bloqueio se registra na hora, com motivo escrito na coluna Bloqueio. Bloqueio sem motivo escrito não conta como bloqueio.
A7: Bloqueio parado há mais de 3 dias úteis sobe para o Lucas, com a decisão pedida por escrito.
A8: O Painel de Demandas (localhost:4321) fica com as tarefas da quinzena, para dar baixa no dia a dia. Quando o painel e o tracker divergirem, o tracker vence.
A10: Status possíveis
A11: Não iniciado · Em andamento · Bloqueado · Em revisão · Concluído. A coluna já vem com lista fechada — não invente status novo.
A12: Em revisão significa: o trabalho acabou e está com outra pessoa ou outra área. Continua sendo seu até voltar.
A14: Prioridade
A15: P0 — sem ela o projeto não existe. P1 — importante, mas o projeto sobrevive. P2 — melhora o resultado.
... A31: Touchpoint terça e quinta, 30 min, só este assunto. Bloco protegido sexta de manhã, 2h. Status quinzenal com o Lucas, 15 min. Comitê de áreas mensal, 1h.

Sheet Tarefas
A1: ID | B1: Fase | C1: Tarefa | D1: Dono | E1: Prioridade | F1: Esforço (h) | G1: Data alvo | H1: Dependência | I1: Status | J1: Bloqueio — motivo | K1: Última atualização | L1: Áreas envolvidas
A2: T1.1 | B2: F1 | C2: Escrever o one-pager de escopo: objetivo, dentro, fora e definição de pronto | D2: Luana | E2: P0 | F2: 3 | G2: 46262 | H2: — | I2: Não iniciado | L2: —
A3: T1.2 | B3: F1 | C3: Fechar as 4 métricas de sucesso com baseline atual e meta | D3: Luana | E3: P0 | F3: 3 | G3: 46269 | H3: T1.1 | I3: Não iniciado | L3: Dados
A4: T1.3 | B4: F1 | C4: Régua de segmentação do long tail: critério objetivo de qual varejo entra | D4: Luiza | E4: P0 | F4: 4 | G4: 46262 | H4: — | I4: Não iniciado | L4: Comercial, Dados
A5: T1.4 | B5: F1 | C5: Assumir o tracker: revisar tarefas, esforços e datas e travar as quatro views | D5: Luana | E5: P0 | F5: 2 | G5: 46269 | H5: — | I5: Não iniciado | L5: —
A6: T1.5 | B6: F1 | C6: Importar as tarefas da quinzena no Painel de Demandas e travar o ritual de baixa | D6: Luiza | E6: P0 | F6: 1 | G6: 46262 | H6: — | I6: Não iniciado | L6: —
A7: T1.6 | B7: F1 | C7: Criar os convites da cadência: touchpoint ter/qui, bloco de sexta, status quinzenal e comitê mensal | D7: Luiza | E7: P0 | F7: 1 | G7: 46269 | H7: — | I7: Não iniciado | L7: —
A8: T1.7 | B8: F1 | C8: Escrever as hipóteses que o piloto precisa testar | D8: Luana | E8: P1 | F8: 2 | G8: 46269 | H8: T1.2 | I8: Não iniciado | L8: —
A9: T1.8 | B9: F1 | C9: Mapa de stakeholders: um ponto focal em Jurídico, Financeiro, People/DP, CS, Dados e MKT | D9: Luiza | E9: P1 | F9: 3 | G9: 46269 | H9: — | I9: Não iniciado | L9: Todas
A10: T1.9 | B10: F1 | C10: Apresentar o enquadramento ao Lucas e fechar o escopo | D10: Luana | E10: P0 | F10: 2 | G10: 46269 | H10: T1.1,T1.2 | I10: Não iniciado | L10: Liderança
A11: T2.1 | B11: F2 | C11: Revisar a transcrição Amanda/Júlia x Thiago e extrair o direcional jurídico mínimo | D11: Luana | E11: P0 | F11: 4 | G11: 46276 | H11: — | I11: Não iniciado | L11: Jurídico
A12: T2.2 | B12: F2 | C12: Lista de red flags e perguntas para o Thiago: o que pode remunerar por modelo, vínculo, exclusividade, uso de marca | D12: Luana | E12: P0 | F12: 2 | G12: 46276 | H12: T2.1 | I12: Não iniciado | L12: Jurídico
A13: T2.3 | B13: F2 | C13: Sessão de 45 min com o Thiago para o direcional (não é o parecer formal) | D13: Luana | E13: P0 | F13: 2 | G13: 46283 | H13: T2.2 | I13: Não iniciado | L13: Jurídico
... A59: T5.6 | B59: F5 | C59: Escrever a recomendação de escalar, ajustar ou encerrar e levar ao Lucas | D59: Luana | E59: P0 | F59: 6 | G59: 46493 | H59: T5.2,T5.3,T5.4 | I59: Não iniciado | L59: Liderança

Sheet Fases
A1: Fases do projeto — uma fase, um dono
A3: Fase | B3: Nome | C3: Dono | D3: Apoio | E3: Início | F3: Fim | G3: Objetivo | H3: Entregável concreto | I3: Critério de saída | J3: Depende de
A4: F1 | B4: Enquadramento | C4: Luana | D4: Luiza | E4: 46260 | F4: 46269 | G4: Fechar escopo, métricas e cadência antes de aprofundar qualquer coisa. | H4: One-pager de escopo + régua de segmentação + tracker no ar | I4: Escopo escrito e aprovado pelo Lucas; 4 métricas com baseline; tracker populado e cadência na agenda. | J4: —
A5: F2 | B5: Descoberta e escolha do modelo | C5: Luana | D5: Luiza | E5: 46273 | F5: 46297 | G5: Saber o que o mercado faz e o que o jurídico proíbe, e escolher UM modelo — sem ainda desenhar remuneração. | H5: Comparativo de modelos com recomendação + direcional jurídico mínimo + baseline de CAC | I5: Um modelo escolhido e defendido ao Lucas, com os red flags jurídicos conhecidos e o inventário da operação levantado. | J5: F1
A6: F3 | B6: Desenho do modelo | C6: Luana | D6: Luiza | E6: 46296 | F6: 46339 | G6: Transformar o modelo escolhido em remuneração, business case, contrato e playbook. | H6: Cenário de remuneração escolhido + business case + minuta de contrato + guias e specs de dash | I6: Remuneração escolhida entre 3 cenários, business case aprovado pelo Financeiro, parecer do Thiago e minuta de contrato pronta. | J6: F2
A7: F4 | B7: Prontidão operacional | C7: Luiza | D7: Luana | E7: 46342 | F7: 46374 | G7: Contratar o parceiro e deixar a operação pronta para ir a campo. | H7: Contrato assinado, dashboards no ar, guias publicados e representante certificado | I7: Checklist de go/no-go assinado: contrato válido, ciclo de pagamento testado, dash no ar, carteira transferida. | J7: F3
A8: F5 | B8: Piloto assistido e decisão | C8: Luiza | D8: Luana | E8: 46398 | F8: 46493 | G8: Rodar a carteira-piloto, apurar três ciclos e decidir escalar, ajustar ou encerrar. | H8: Piloto em campo + 3 apurações + recomendação formal ao Lucas | I8: Recomendação entregue com leitura das hipóteses e do business case real contra o modelado. | J8: F4

Sheet Escopo
A1: Escopo fechado
A3: DENTRO do escopo | C3: FORA do escopo — não faremos agora
A4: • Desenhar e escolher o modelo de terceirização da operação do long tail regional | C4: • Terceirizar varejo corporate — segue com o time interno da UME
A5: • Validar juridicamente o modelo e o formato de remuneração | C5: • Prospecção e venda de novos varejos pelo representante (decisão Q1; fora do piloto de qualquer forma)
A6: • Definir a remuneração, as regras de apuração e o business case | C6: • Rebate e MDR para o representante — só existe se a Q1 virar sim
A7: • Redigir a minuta de contrato e a matriz de alçadas do representante | C7: • Automatizar o cadastro de lojas e operadores — fica com o time da Amanda e vira backlog de Tech
A8: • Montar o onboarding do representante e o do varejo, tocado por ele | C8: • Modelo de franquia e licenciamento de marca — descartado em 26/ago
A9: • Especificar e publicar o dash de operação e o dash financeiro com export CSV | C9: • Criar um time interno de N2 dedicado ao canal terceirizado
A10: • Publicar repositório de trade, brand book, FAQ e canais de atendimento | C10: • Mudar política de crédito, alçadas de aprovação ou qualquer coisa em produção
A11: • Selecionar e contratar UM parceiro para o piloto | C11: • Onda 2 de representantes e expansão nacional — só depois do Gate 5
A12: • Rodar o piloto por 3 ciclos de apuração e recomendar escalar, ajustar ou encerrar | C12: • Uniforme ou identidade visual obrigatória para o representante — vira recomendação, por risco de vínculo
A15: Definição de pronto — o projeto acabou quando:
A16: • existe um representante terceirizado rodando uma carteira long tail com contrato assinado;
A17: • a remuneração foi apurada e paga por 3 ciclos, com o business case real medido contra o modelado;
A18: • o playbook (onboarding, guias, dashboards, FAQ) está publicado e foi usado por alguém de fora da UME;
A19: • o time interno consegue mostrar, com número, quantas horas por semana deixou de gastar com esses varejos;
A20: • a recomendação de escalar, ajustar ou encerrar foi entregue ao Lucas e decidida.

Sheet Métricas
A1: Métricas de sucesso
A3: ID | B3: Métrica de sucesso | C3: Baseline hoje | D3: Meta | E3: Dono | F3: Onde se mede | G3: Valor atual | H3: Atualizado em
A4: M1 | B4: Horas/semana do time interno gastas com varejo long tail | C4: A medir na F1 (amostra de 2 semanas) | D4: -60% até o fim do piloto | E4: Luana | F4: Apontamento das duas + agenda
A5: M2 | B5: Varejos ativos sob carteira terceirizada | C5: 0 | D5: 10 a 15 lojas no piloto | E5: Luiza | F5: Dash de operação
A6: M3 | B6: CAC do canal terceirizado (R$ por novo cliente) | C6: R$ 14 (referência da central de vendas) | D6: Menor ou igual a R$ 14, com teto de 2% sobre originação | E6: Luana | F6: Apuração mensal
A7: M4 | B7: FPD e inadimplência da carteira terceirizada | C7: A medir (média UME por região) | D7: Até 1 p.p. acima da média UME | E7: Luana | F7: Risco / BigQuery
A8: M5 | B8: Originação da carteira-piloto contra o mesmo período do ano anterior | C8: A medir na F4 | D8: +15% no 3º ciclo | E8: Luiza | F8: Dash financeiro

Sheet Riscos
A1: Top 5 riscos
A3: ID | B3: Risco | C3: Probabilidade | D3: Impacto | E3: Sinal de alerta antecipado | F3: Mitigação | G3: Dono do risco | H3: Status
A4: R1 | B4: Remuneração mal calibrada: pagar sobre originação total estoura o CAC e o modelo deixa de se pagar | C4: Alta | D4: Alto | E4: No 1º cenário modelado, o custo por novo cliente passa de R$ 14 sem contrapartida de volume | F4: Ancorar em CAC/novos clientes com guardrails de FPD e MOIC, teto por carteira e cláusula de revisão a cada 6 meses | G4: Luana | H4: Vigiando
A5: R2 | B5: Uma restrição jurídica invalida o modelo depois de desenhado | C5: Média | D5: Alto | E5: O direcional do Thiago (T2.3) vem com 'depende' em vez de 'pode/não pode' | F5: Direcional mínimo na F2, antes de modelar remuneração; três cenários levados ao parecer em vez de um | G5: Luana | H5: Vigiando
A6: R3 | B6: Escopo infla: querer resolver engajamento, prospecção de varejo e comercial no mesmo pacote | C6: Alta | D6: Alto | E6: Aparece tarefa de rebate ou MDR no tracker sem decisão do Gate 2 | F6: Lista de fora de escopo assinada na F1; prospecção só entra se a Q1 for decidida como sim, e mesmo assim fora do piloto | G6: Luana | H6: Vigiando
A7: R4 | B7: As 8h/semana não se sustentam quando a operação do dia a dia aperta | C7: Alta | D7: Alto | E7: Duas semanas seguidas com menos de 5h apontadas, ou touchpoint desmarcado 2x | F7: Bloco de sexta protegido na agenda; se a semana cair abaixo de 5h, corta-se P2 antes de empurrar P0; capacidade revista no status quinzenal | G7: Luiza | H7: Vigiando
A8: R5 | B8: Cadastro e acessos presos no time da Amanda viram o gargalo da operação terceirizada | C8: Média | D8: Médio | E8: Qualquer pedido de acesso do piloto levando mais de 48h | F8: SLA escrito na T3.15, com fila visível; automação vira backlog priorizado de Tech antes da onda 2 | G8: Luiza | H8: Vigiando

Sheet Carga semanal
A1: Realidade da capacidade — 8h/semana por pessoa, já descontado feriado
A3: Semana (segunda) | B3: Capacidade (h) | C3: Luana (h) | D3: Luiza (h) | E3: Folga Luana | F3: Folga Luiza
A4: 46258 | B4: 5 | C4: 5 | D4: 5 | E4: 0 | F4: 0
A5: 46265 | B5: 8 | C5: 7 | D5: 4 | E5: 1 | F5: 4
A6: 46272 | B6: 6.4 | C6: 6.4 | D6: 6.4 | E6: 0 | F6: 0
A7: 46279 | B7: 8 | C7: 8 | D7: 8 | E7: 0 | F7: 0
A8: 46286 | B8: 8 | C8: 8 | D8: 6.6 | E8: 0 | F8: 1.4
A9: 46293 | B9: 8 | C9: 8 | D9: 8 | E9: 0 | F9: 0
A10: 46300 | B10: 8 | C10: 8 | D10: 8 | E10: 0 | F10: 0
A11: 46307 | B11: 6.4 | C11: 6.4 | D11: 6.4 | E11: 0 | F11: 0
A12: 46314 | B12: 8 | C12: 8 | D12: 8 | E12: 0 | F12: 0
A13: 46321 | B13: 8 | C13: 8 | D13: 8 | E13: 0 | F13: 0
A14: 46328 | B14: 6.4 | C14: 6.2 | D14: 6.4 | E14: 0.2 | F14: 0
A15: 46335 | B15: 8 | C15: 0 | D15: 5.2 | E15: 8 | F15: 2.8
... A28: 46489 | B28: 8 | C28: 3.6 | D28: 0 | E28: 4.4 | F28: 8

Sheet V · Vence em 7 dias
A1: ID | B1: Fase | C1: Tarefa | D1: Dono | E1: Prioridade | F1: Esforço (h) | G1: Data alvo | H1: Dependência | I1: Status | J1: Bloqueio — motivo
A2: =SORT(FILTER(Tarefas!A4:J61, Tarefas!G4:G61<=TODAY()+7, Tarefas!I4:I61<>"Concluído"), 7, TRUE)

Sheet V · Bloqueios
A1: ID | B1: Fase | C1: Tarefa | D1: Dono | E1: Prioridade | F1: Esforço (h) | G1: Data alvo | H1: Dependência | I1: Status | J1: Bloqueio — motivo
A2: =FILTER(Tarefas!A4:J61, Tarefas!I4:I61="Bloqueado")

Sheet V · Luana
A1: ID | B1: Fase | C1: Tarefa | D1: Dono | E1: Prioridade | F1: Esforço (h) | G1: Data alvo | H1: Dependência | I1: Status | J1: Bloqueio — motivo
A2: =SORT(FILTER(Tarefas!A4:J61, Tarefas!D4:D61="Luana", Tarefas!I4:I61<>"Concluído"), 7, TRUE)

Sheet V · Luiza
A1: ID | B1: Fase | C1: Tarefa | D1: Dono | E1: Prioridade | F1: Esforço (h) | G1: Data alvo | H1: Dependência | I1: Status | J1: Bloqueio — motivo
A2: =SORT(FILTER(Tarefas!A4:J61, Tarefas!D4:D61="Luiza", Tarefas!I4:I61<>"Concluído"), 7, TRUE)

Sheet Para o Painel
A1: Linhas prontas para colar no Importar do Painel de Demandas
A2: Formato do painel: cluster | conta | responsável | AAAA-MM-DD | descrição. Copie só as linhas da quinzena.
A4: Linha
A5: ="novos | Terceirização | "&Tarefas!D4&" | "&TEXT(Tarefas!G4,"yyyy-mm-dd")&" | ["&Tarefas!A4&"] "&Tarefas!C4
A6: ="novos | Terceirização | "&Tarefas!D5&" | "&TEXT(Tarefas!G5,"yyyy-mm-dd")&" | ["&Tarefas!A5&"] "&Tarefas!C5
A7: ="novos | Terceirização | "&Tarefas!D6&" | "&TEXT(Tarefas!G6,"yyyy-mm-dd")&" | ["&Tarefas!A6&"] "&Tarefas!C6
A8: ="novos | Terceirização | "&Tarefas!D7&" | "&TEXT(Tarefas!G7,"yyyy-mm-dd")&" | ["&Tarefas!A7&"] "&Tarefas!C7
A9: ="novos | Terceirização | "&Tarefas!D8&" | "&TEXT(Tarefas!G8,"yyyy-mm-dd")&" | ["&Tarefas!A8&"] "&Tarefas!C8
A10: ="novos | Terceirização | "&Tarefas!D9&" | "&TEXT(Tarefas!G9,"yyyy-mm-dd")&" | ["&Tarefas!A9&"] "&Tarefas!C9
A11: ="novos | Terceirização | "&Tarefas!D10&" | "&TEXT(Tarefas!G10,"yyyy-mm-dd")&" | ["&Tarefas!A10&"] "&Tarefas!C10
A12: ="novos | Terceirização | "&Tarefas!D11&" | "&TEXT(Tarefas!G11,"yyyy-mm-dd")&" | ["&Tarefas!A11&"] "&Tarefas!C11
A13: ="novos | Terceirização | "&Tarefas!D12&" | "&TEXT(Tarefas!G12,"yyyy-mm-dd")&" | ["&Tarefas!A12&"] "&Tarefas!C12
A14: ="novos | Terceirização | "&Tarefas!D13&" | "&TEXT(Tarefas!G13,"yyyy-mm-dd")&" | ["&Tarefas!A13&"] "&Tarefas!C13
A15: ="novos | Terceirização | "&Tarefas!D14&" | "&TEXT(Tarefas!G14,"yyyy-mm-dd")&" | ["&Tarefas!A14&"] "&Tarefas!C14
A16: ="novos | Terceirização | "&Tarefas!D15&" | "&TEXT(Tarefas!G15,"yyyy-mm-dd")&" | ["&Tarefas!A15&"] "&Tarefas!C15
... A62: ="novos | Terceirização | "&Tarefas!D61&" | "&TEXT(Tarefas!G61,"yyyy-mm-dd")&" | ["&Tarefas!A61&"] "&Tarefas!C61
